{
 "id": "21ebfafe-f248-4992-93a3-b6ae54668cfc",
 "title": {
  "en": "The Young Master Who Ran Away from His Marriage"
 },
 "contentRating": "safe",
 "matches": [
  {
   "id": "7f80d669-d5d7-49f6-bb21-d578f28fb2e7",
   "title": {
    "en": "My Wife Is Cold-Hearted"
   },
   "contentRating": "safe",
   "score": 0.5021298,
   "languages": [
    "en",
    "tr",
    "fr"
   ],
   "coverFileName": "a5d18492-b97f-49be-a434-bec3ec914aa4.png"
  },
  {
   "id": "4f564228-d4ee-4efe-b04e-f73f6a9c5fb5",
   "title": {
    "en": "Yesterday was like Death"
   },
   "contentRating": "safe",
   "score": 0.49961278,
   "languages": [
    "es-la",
    "en"
   ],
   "coverFileName": "ad2dd7e5-a56a-4bdd-bc1e-7c9e27279450.jpg"
  },
  {
   "id": "892cba92-cdd2-4507-9094-01bb7e9d4fab",
   "title": {
    "en": "Silent Lover"
   },
   "contentRating": "safe",
   "score": 0.4924803,
   "languages": [
    "es-la",
    "en"
   ],
   "coverFileName": "111b911b-20fb-44dd-aeca-6be292fefb97.png"
  },
  {
   "id": "129edf80-21e4-4799-9c0f-1c942400ec73",
   "title": {
    "en": "Fei Xi Yan Xue"
   },
   "contentRating": "safe",
   "score": 0.48793986,
   "languages": [
    "en"
   ],
   "coverFileName": "7581b024-67a6-45fb-91f4-24cf17b4605d.jpg"
  },
  {
   "id": "ecee2441-4cf3-410c-9c96-45c99e1d9a3a",
   "title": {
    "en": "Boss of the Emperor's Harem"
   },
   "contentRating": "safe",
   "score": 0.44343197,
   "languages": [
    "en",
    "fr"
   ],
   "coverFileName": "6df7f796-7840-4042-a35a-00ce2d6ed8fa.jpg"
  },
  {
   "id": "95ff5472-219e-4a15-b41c-4389cce172f5",
   "title": {
    "en": "Full Marks, Hidden Marriage"
   },
   "contentRating": "safe",
   "score": 0.42632547,
   "languages": [
    "en",
    "tr"
   ],
   "coverFileName": "13b89ed7-b07e-4f06-b235-9735cd0d51c8.jpg"
  },
  {
   "id": "b49bb16c-bcc9-48d0-b7fd-c382c57a9c00",
   "title": {
    "en": "Sworn Enemy or Lover?"
   },
   "contentRating": "safe",
   "score": 0.4261239,
   "languages": [
    "es-la",
    "en"
   ],
   "coverFileName": "021637d8-3238-4300-948d-627694f5fc5c.jpg"
  },
  {
   "id": "2d305864-8641-440c-9870-8ae68ea045b4",
   "title": {
    "en": "Love Is a Cherry Color"
   },
   "contentRating": "safe",
   "score": 0.42353868,
   "languages": [
    "en",
    "es",
    "fr"
   ],
   "coverFileName": "dd0661a7-c8cd-4c3a-9dde-e61e10e3e6e3.jpg"
  },
  {
   "id": "7642ae5a-57c8-41d2-aa88-c13dbab8e862",
   "title": {
    "en": "Forced Marriage, True Love"
   },
   "contentRating": "safe",
   "score": 0.42112452,
   "languages": [
    "en",
    "id"
   ],
   "coverFileName": "f158d45e-dc38-4fa8-9f53-aa12a193181e.png"
  },
  {
   "id": "ef7cfd96-d703-41a5-98f9-3cc65020be9d",
   "title": {
    "en": "Olive's Plan To Get Rich"
   },
   "contentRating": "safe",
   "score": 0.40642986,
   "languages": [
    "en"
   ],
   "coverFileName": "611d56d0-9c3d-4262-8892-45ab14bd9327.png"
  },
  {
   "id": "95929ed7-6b14-4ce4-820c-3ece99eeccba",
   "title": {
    "en": "Stop Bothering Me, Emperor!"
   },
   "contentRating": "safe",
   "score": 0.4031691,
   "languages": [
    "it",
    "en"
   ],
   "coverFileName": "7dbca5f9-9fa1-4296-8315-9fd906814911.png"
  },
  {
   "id": "6dfef8eb-a32a-4729-b854-995346321ed5",
   "title": {
    "en": "Your Distance"
   },
   "contentRating": "safe",
   "score": 0.40081382,
   "languages": [
    "en",
    "es-la"
   ],
   "coverFileName": "2284f650-a612-4655-98da-8a79f4ec8ae5.jpg"
  }
 ],
 "updatedAt": "2021-07-18T06:30:48+00:00",
 "coverFileName": "0ade8f74-e4d4-45ca-87fe-0ffde9fd6ed1.jpg"
}