{
 "id": "2f86d265-fc88-41db-929e-5dab9ac74352",
 "title": {
  "en": "Mario"
 },
 "contentRating": "safe",
 "matches": [
  {
   "id": "bb9d7179-8465-45ea-9806-215b38f2be7d",
   "title": {
    "en": "Onihime"
   },
   "contentRating": "safe",
   "score": 0.45,
   "languages": [
    "en"
   ],
   "coverFileName": "8be43515-a75f-4e0a-8af9-eda5df8ba775.jpg"
  },
  {
   "id": "5505e114-a90b-4d5b-a3a3-de24fc313a95",
   "title": {
    "en": "Goblin Knight"
   },
   "contentRating": "safe",
   "score": 0.41521275,
   "languages": [
    "en"
   ],
   "coverFileName": "823e4553-1783-4a0c-a13b-ff81f44626b0.jpg"
  },
  {
   "id": "d139f4b1-b782-4fdd-b006-35520f14a847",
   "title": {
    "en": "Sekishin"
   },
   "contentRating": "safe",
   "score": 0.38971144,
   "languages": [
    "en"
   ],
   "coverFileName": "809bd702-b015-4e17-832b-fe0bfac7390c.jpg"
  },
  {
   "id": "980afc65-7534-4c58-9954-15ed944fd585",
   "title": {
    "en": "Black Mind"
   },
   "contentRating": "safe",
   "score": 0.38971144,
   "languages": [
    "en",
    "pl"
   ],
   "coverFileName": "3e1369f3-b38e-4dad-b92a-285b25689419.jpg"
  },
  {
   "id": "523ab7de-2ec8-4e8f-9674-1631a318bb36",
   "title": {
    "en": "Hello Baby"
   },
   "contentRating": "safe",
   "score": 0.38971144,
   "languages": [
    "pl",
    "ro",
    "de",
    "en",
    "ca",
    "hu"
   ],
   "coverFileName": "61b95c6f-8070-4a87-aaf0-beaf74e2ab0f.jpg"
  },
  {
   "id": "025c4e6a-4636-4c7d-a2d0-281674ad080d",
   "title": {
    "en": "Little War"
   },
   "contentRating": "safe",
   "score": 0.36742347,
   "languages": [
    "fr",
    "pt-br",
    "en"
   ],
   "coverFileName": "6543a6cd-ddcd-4c1b-a041-eb197113b619.jpg"
  },
  {
   "id": "591eb5e6-22b8-44e6-9db4-cbb8788eb3e8",
   "title": {
    "en": "Another Vanguard - Vanguard Frontier"
   },
   "contentRating": "safe",
   "score": 0.36742347,
   "languages": [
    "en"
   ],
   "coverFileName": "e76c1f7e-0a05-4017-ab75-32392a0faecb.jpg"
  },
  {
   "id": "99b3c4fd-6a90-44c4-bf03-ee7308b1b05e",
   "title": {
    "en": "Karakuri"
   },
   "contentRating": "safe",
   "score": 0.36742347,
   "languages": [
    "en",
    "it",
    "pl"
   ],
   "coverFileName": "b2fb6c53-40d2-491f-8161-ac4ad8978b04.jpg"
  },
  {
   "id": "94eb0afc-293c-4323-96b8-89c46de463e6",
   "title": {
    "en": "Gokurakugai Sanbandori no Ken"
   },
   "contentRating": "safe",
   "score": 0.36742347,
   "languages": [
    "id",
    "ar",
    "ca",
    "fr",
    "ru",
    "pt-br",
    "es-la",
    "vi",
    "it",
    "en"
   ],
   "coverFileName": "e588fad2-dbcf-4ca3-a1c1-e1697e917922.jpg"
  },
  {
   "id": "006a499e-cb23-42eb-bb60-d6ad8b4bd427",
   "title": {
    "en": "Ryuudan Shounen"
   },
   "contentRating": "safe",
   "score": 0.36742347,
   "languages": [
    "en"
   ],
   "coverFileName": "29ac5b9f-a360-4f29-b4d7-69a24cdf58f8.jpg"
  },
  {
   "id": "f25e0525-a016-4575-92b3-45c7cd1d2c7b",
   "title": {
    "en": "Minds"
   },
   "contentRating": "safe",
   "score": 0.36742347,
   "languages": [
    "pl",
    "en"
   ],
   "coverFileName": "12999b00-0666-45da-b0c9-925b723cf90b.jpg"
  },
  {
   "id": "d40aa845-bc0b-4c34-a5eb-99cf973e3935",
   "title": {
    "en": "Kesshoku no Shuugosha"
   },
   "contentRating": "safe",
   "score": 0.3485685,
   "languages": [
    "en"
   ],
   "coverFileName": "74b934ed-18bd-4f17-9704-63d4ede7c778.jpg"
  }
 ],
 "updatedAt": "2021-07-18T06:33:18+00:00",
 "coverFileName": "ac6600cc-4029-4142-b859-6a732b3120ce.jpg"
}