{
 "id": "3bdd0f2d-2d17-4e92-8798-c0fa3861f9c9",
 "title": {
  "en": "Olanda-san"
 },
 "contentRating": "safe",
 "matches": [
  {
   "id": "b8db8f7b-8dca-4518-a56e-9bbde31f7383",
   "title": {
    "en": "Gichi Gichi-kun"
   },
   "contentRating": "safe",
   "score": 0.59693664,
   "languages": [
    "en"
   ],
   "coverFileName": "91ce6abc-291c-4537-912f-e4545df4e325.jpg"
  },
  {
   "id": "5cff4e88-e6b7-4a75-a1be-ec975f6bfd75",
   "title": {
    "en": "Metroid Prime: Episode of Aether"
   },
   "contentRating": "safe",
   "score": 0.56078446,
   "languages": [
    "en"
   ],
   "coverFileName": "704cc365-c3b9-4e28-a46d-ef693ba46a42.jpg"
  },
  {
   "id": "5cd9c5ae-2853-4dce-8a9d-639f0fc67f80",
   "title": {
    "en": "Sugars"
   },
   "contentRating": "safe",
   "score": 0.55689394,
   "languages": [
    "en"
   ],
   "coverFileName": "4ea59e2d-30fe-44ae-b26c-95e438bccfbf.jpg"
  },
  {
   "id": "bb0e9e88-e44b-442a-9ad3-19099af31b76",
   "title": {
    "en": "The Man who Killed Nobunaga"
   },
   "contentRating": "safe",
   "score": 0.5430257,
   "languages": [
    "en"
   ],
   "coverFileName": "7f1f9e9b-2c83-4a8a-90f3-597d9a8328bd.jpg"
  },
  {
   "id": "ff203e58-765a-4c83-9088-fd6fb32d710b",
   "title": {
    "en": "Kyo"
   },
   "contentRating": "safe",
   "score": 0.52947617,
   "languages": [
    "en"
   ],
   "coverFileName": "7200c607-7169-499f-bc19-a70b4c963ff0.jpg"
  },
  {
   "id": "d72fb2d5-6fb4-478a-acd8-88586829ebcb",
   "title": {
    "en": "Waltz"
   },
   "contentRating": "safe",
   "score": 0.5290904,
   "languages": [
    "en",
    "ar"
   ],
   "coverFileName": "61c6f6e2-980d-4c5a-8de4-5dd10cc1e22f.jpg"
  },
  {
   "id": "677b6ebf-181f-4241-9f20-3211c9e058a4",
   "title": {
    "en": "Spring's Espresso"
   },
   "contentRating": "safe",
   "score": 0.5287923,
   "languages": [
    "en",
    "fr"
   ],
   "coverFileName": "bfe217c4-e4c6-4050-83ed-f992df73cabf.jpg"
  },
  {
   "id": "c433f163-d610-49ba-a031-a1f3b6377af2",
   "title": {
    "en": "Baby Steps"
   },
   "contentRating": "safe",
   "score": 0.52797014,
   "languages": [
    "pt-br",
    "en",
    "it",
    "pl",
    "fr"
   ],
   "coverFileName": "2b62ace5-2397-4ff7-8cf3-b5a9b0cf9001.png"
  },
  {
   "id": "6a200bd7-8391-407a-8c3c-49e215abc5a8",
   "title": {
    "en": "Yuunagi no Machi Sakura no Kuni"
   },
   "contentRating": "safe",
   "score": 0.52242804,
   "languages": [
    "en",
    "ar"
   ],
   "coverFileName": "1ea5b273-d9c5-4521-ab2d-228e7c0aab98.jpg"
  },
  {
   "id": "7d554c01-82c8-43ff-aaf5-5c68a9e51e79",
   "title": {
    "en": "Kagerou Inazuma Mizu no Tsuki"
   },
   "contentRating": "safe",
   "score": 0.5223273,
   "languages": [
    "ru",
    "en"
   ],
   "coverFileName": "934f3aba-af57-42fc-ae40-3d11fc086ce8.jpg"
  },
  {
   "id": "1ee751ff-0860-41ef-87f5-d05884d10770",
   "title": {
    "en": "My Beautiful World"
   },
   "contentRating": "safe",
   "score": 0.5219479,
   "languages": [
    "en",
    "tr"
   ],
   "coverFileName": "223fec3c-2027-4bf8-887c-b362616440a7.jpg"
  },
  {
   "id": "6b62ae51-b3ac-4ca9-81fa-4912070f313a",
   "title": {
    "en": "The Three Times"
   },
   "contentRating": "safe",
   "score": 0.5153063,
   "languages": [
    "en"
   ],
   "coverFileName": "9addf4c3-9083-4802-915c-8682e57d2948.jpg"
  }
 ],
 "updatedAt": "2021-07-18T06:35:37+00:00",
 "coverFileName": "c1e4c247-3c18-46dd-88a4-f26d4d55b8ec.jpg"
}