{
 "id": "5227abca-3d3d-4456-92ff-e67f6e8eb0ee",
 "title": {
  "en": "School Zone"
 },
 "contentRating": "safe",
 "matches": [
  {
   "id": "a4e5418c-18d9-468a-8cac-8daa78617f83",
   "title": {
    "en": "Furidashi ni Ochiru!"
   },
   "contentRating": "safe",
   "score": 0.449724,
   "languages": [
    "en",
    "id"
   ],
   "coverFileName": "3de71bb8-5149-4135-b39f-62410093947b.jpg"
  },
  {
   "id": "f1e48531-cf26-4b6d-adef-b4641d77447d",
   "title": {
    "en": "Opapagoto"
   },
   "contentRating": "safe",
   "score": 0.42781,
   "languages": [
    "en",
    "es"
   ],
   "coverFileName": "a8c3c62a-8200-4cc4-b11d-7cc39ecde23b.jpg"
  },
  {
   "id": "71d9dccd-4f16-4ce6-beac-dc084706c735",
   "title": {
    "en": "Ike! Danshi Koukou Engekibu"
   },
   "contentRating": "safe",
   "score": 0.42389843,
   "languages": [
    "en",
    "pl"
   ],
   "coverFileName": "92207fae-b1e6-4b45-b230-4d00ef4450b6.jpg"
  },
  {
   "id": "e182b09f-09ab-4201-8f37-0ced6822eb39",
   "title": {
    "en": "Watashi ga Motenai no wa Dou Kangaetemo Omaera ga Warui!"
   },
   "contentRating": "safe",
   "score": 0.42245245,
   "languages": [
    "zh",
    "it",
    "en",
    "fr",
    "pt-br",
    "pl"
   ],
   "coverFileName": "c9be5e48-ea5b-4cee-a72c-d12c6d3b4d0e.jpg"
  },
  {
   "id": "43df19d5-0990-46ec-9367-ea29c502e7bb",
   "title": {
    "en": "Come Rain or Shine"
   },
   "contentRating": "safe",
   "score": 0.41876164,
   "languages": [
    "en",
    "id"
   ],
   "coverFileName": "58494c16-2880-4dd0-970a-724c573e51c9.jpg"
  },
  {
   "id": "8d7a123b-3d64-4eea-9dd0-000e94be1852",
   "title": {
    "en": "Futari Monologue"
   },
   "contentRating": "safe",
   "score": 0.408181,
   "languages": [
    "en"
   ],
   "coverFileName": "1f919e68-5ff8-4f33-a780-6b62b6a25b1b.jpg"
  },
  {
   "id": "75e35f38-f74e-4356-84d9-084d022a21b0",
   "title": {
    "en": "Riko to Haru to Onsen to Iruka"
   },
   "contentRating": "safe",
   "score": 0.408181,
   "languages": [
    "en",
    "ru",
    "es-la"
   ],
   "coverFileName": "4e9c5adf-18b0-44c4-96b4-40a599817812.jpg"
  },
  {
   "id": "2f1a2700-662e-4f6f-b0f8-24aeb274d839",
   "title": {
    "en": "Urami-san wa Kyou mo Ayaui"
   },
   "contentRating": "safe",
   "score": 0.40563056,
   "languages": [
    "en",
    "es-la"
   ],
   "coverFileName": "0cd79ae7-1fb5-4293-8289-7cb24409b3a0.jpg"
  },
  {
   "id": "90fab1f9-1beb-4a6e-986f-eaf8a0616409",
   "title": {
    "en": "Lemonade"
   },
   "contentRating": "safe",
   "score": 0.4021432,
   "languages": [
    "en"
   ],
   "coverFileName": "55feac0f-0af8-4c9c-aa87-a70901a361fe.jpg"
  },
  {
   "id": "e850e497-2d50-40cc-a0da-186e3857e33a",
   "title": {
    "en": "Mahou Tsukai no Hako - Starlit Marmalade"
   },
   "contentRating": "safe",
   "score": 0.39874268,
   "languages": [
    "en"
   ],
   "coverFileName": "a10bf31e-007b-4289-befd-9485a9413320.jpg"
  },
  {
   "id": "f2fdd80f-1aa2-416a-83e2-7818bec25cf1",
   "title": {
    "en": "Kamichu!"
   },
   "contentRating": "safe",
   "score": 0.39681134,
   "languages": [
    "ru",
    "es",
    "en"
   ],
   "coverFileName": "c3649bb4-cf57-43e7-8dd1-aabe3cbb4ca8.jpg"
  },
  {
   "id": "2d282b5e-599d-4915-83ba-42b69c42954b",
   "title": {
    "en": "Kuzumi-kun, Kuuki Yometemasu ka?"
   },
   "contentRating": "safe",
   "score": 0.3958611,
   "languages": [
    "ru",
    "en",
    "pt-br",
    "id"
   ],
   "coverFileName": "e6f140d7-b620-4132-8e4d-cc20ec63dc01.png"
  }
 ],
 "updatedAt": "2021-07-18T06:39:45+00:00",
 "coverFileName": "86a5f794-2957-4389-9d73-79a6f5a1f5c5.jpg"
}