{
 "id": "7260f712-2800-44d3-95dc-31ae49797150",
 "title": {
  "en": "THE iDOLM@STER - IoRIx *Dream* (Doujinshi)"
 },
 "contentRating": "pornographic",
 "matches": [
  {
   "id": "644c5cd6-31cd-4f76-ade3-c4e2e8226ff3",
   "title": {
    "en": "Purimu no Nikki"
   },
   "contentRating": "pornographic",
   "score": 0.5119689,
   "languages": [
    "en"
   ],
   "coverFileName": "0d340b34-85ba-4998-9baf-42f80ca38fae.jpg"
  },
  {
   "id": "7eba5736-e413-4e77-a81f-94cb213ba0d9",
   "title": {
    "en": "Risou no Imouto Saimin-hen"
   },
   "contentRating": "pornographic",
   "score": 0.48610398,
   "languages": [
    "en"
   ],
   "coverFileName": "cea2caaa-9343-424d-93a1-dadb0604ead1.png"
  },
  {
   "id": "f578ad40-33ff-4008-9991-ad132a765307",
   "title": {
    "en": "No Dog No Life"
   },
   "contentRating": "pornographic",
   "score": 0.4830388,
   "languages": [
    "en"
   ],
   "coverFileName": "840199fa-c7a0-4a34-b6c6-37a5478e0cf6.jpg"
  },
  {
   "id": "f7884ed6-167e-4e30-9029-db51ff2e16f0",
   "title": {
    "en": "Young Boss"
   },
   "contentRating": "pornographic",
   "score": 0.48278502,
   "languages": [
    "pt-br",
    "en"
   ],
   "coverFileName": "6b8d9495-a3ce-4302-9170-a3c7893948cf.jpg"
  },
  {
   "id": "47a0c0dc-57bf-433e-8389-978808b8961b",
   "title": {
    "en": "Glass no Megami"
   },
   "contentRating": "pornographic",
   "score": 0.48174796,
   "languages": [
    "en"
   ],
   "coverFileName": "5b02ebc6-14f6-4e9c-8f58-2d698adc6256.jpg"
  },
  {
   "id": "2205b1bc-a1a1-4bcc-b343-b81a806be5c9",
   "title": {
    "en": "My Ideal Isekai Life"
   },
   "contentRating": "pornographic",
   "score": 0.48019412,
   "languages": [
    "ru",
    "en"
   ],
   "coverFileName": "3058abf2-546a-4060-a09b-7076f15db03b.png"
  },
  {
   "id": "dd1877dd-056b-4c14-82e3-040f02b7eaed",
   "title": {
    "en": "Do I Smell?"
   },
   "contentRating": "pornographic",
   "score": 0.47795215,
   "languages": [
    "en"
   ],
   "coverFileName": "0d5f9023-51ba-480d-8511-4a07571a79a4.png"
  },
  {
   "id": "305d1835-f541-4281-b4e7-16e76aae488a",
   "title": {
    "en": "Parade!"
   },
   "contentRating": "pornographic",
   "score": 0.47680664,
   "languages": [
    "en"
   ],
   "coverFileName": "16193317-bc84-4dc7-8b80-a687e1292863.png"
  },
  {
   "id": "d70a52eb-f49f-4d33-b2f3-6d4dd439bc13",
   "title": {
    "en": "Romantic Joutou"
   },
   "contentRating": "pornographic",
   "score": 0.47670263,
   "languages": [
    "en"
   ],
   "coverFileName": "e6fd781a-cba9-486e-a133-53c814630bd3.jpg"
  },
  {
   "id": "172be989-a54a-4757-9312-1cd3d3ffddea",
   "title": {
    "en": "Kantoku, Nekona Ore wa Dame desu ka"
   },
   "contentRating": "pornographic",
   "score": 0.4752364,
   "languages": [
    "en"
   ],
   "coverFileName": "02f32f7a-4814-47ed-a572-8d990669fc67.jpg"
  },
  {
   "id": "33db421d-18c2-4995-8458-eaf0545288dc",
   "title": {
    "en": "Zettai Renai Shugi"
   },
   "contentRating": "pornographic",
   "score": 0.47439653,
   "languages": [
    "en"
   ],
   "coverFileName": "ff5535f9-bba2-47ac-9b03-3b8cada43dfe.jpg"
  },
  {
   "id": "4e5030e6-3fc6-453b-bd51-7d9edf9140d5",
   "title": {
    "en": "Slow Step"
   },
   "contentRating": "pornographic",
   "score": 0.4738872,
   "languages": [
    "en"
   ],
   "coverFileName": "c183781c-7ec2-4e10-b77e-d1a4dd080330.jpg"
  }
 ],
 "updatedAt": "2021-07-18T06:45:39+00:00",
 "coverFileName": "29c5dd40-1ffb-44a7-a9ad-79eba943182b.jpg"
}