{
 "id": "bbc3c18c-d05f-4081-830a-225b6e0ad540",
 "title": {
  "en": "Seijo no Yurikago, Dokujo no Hitsugi"
 },
 "contentRating": "suggestive",
 "matches": [
  {
   "id": "4c4feee0-7307-4532-b6c6-cbb552d61529",
   "title": {
    "en": "The City of Imprisoned Love"
   },
   "contentRating": "suggestive",
   "score": 0.2670259,
   "languages": [
    "zh-hk",
    "ru",
    "pt-br",
    "es-la",
    "id",
    "en"
   ],
   "coverFileName": "e53b1b1a-65f4-4f89-8f05-bc6524ba52ad.jpg"
  },
  {
   "id": "9a1fe7f8-dda3-4a94-8108-afef8b451e42",
   "title": {
    "en": "Tenkuu Shinpan"
   },
   "contentRating": "suggestive",
   "score": 0.25694576,
   "languages": [
    "ru",
    "en",
    "it"
   ],
   "coverFileName": "9363f328-b0df-4912-bd7b-6ea2ab19cd1b.jpg"
  },
  {
   "id": "5d96047c-4820-4a59-abd7-59c2f662b6e7",
   "title": {
    "en": "Boku to Akumu to Oneesan"
   },
   "contentRating": "suggestive",
   "score": 0.24820483,
   "languages": [
    "en"
   ],
   "coverFileName": "7286ff2e-0bd4-44b7-9eca-cb897cb2438e.jpg"
  },
  {
   "id": "f390fd11-583a-4441-8d88-9c4ac0e5a2b6",
   "title": {
    "en": "Tokyo Mercenary Soldiers Co., LTD"
   },
   "contentRating": "suggestive",
   "score": 0.22657897,
   "languages": [
    "zh-hk",
    "en"
   ],
   "coverFileName": "0116a18f-0462-4a28-8275-627495d593c2.jpg"
  },
  {
   "id": "6cde8524-b52c-4b39-aba6-dc5d1104c29a",
   "title": {
    "en": "Deathdeus: Hero of the Dead"
   },
   "contentRating": "suggestive",
   "score": 0.22252156,
   "languages": [
    "en"
   ],
   "coverFileName": "451f9c2b-dc92-4939-8cb3-b95ab9cf57d9.jpg"
  },
  {
   "id": "deaaa7d0-eba1-46ab-8961-70be94759a2b",
   "title": {
    "en": "Goumaden Shutendouji"
   },
   "contentRating": "suggestive",
   "score": 0.20977136,
   "languages": [
    "en"
   ],
   "coverFileName": "6b19d95f-2a81-4019-a9a4-4ed2333416a3.jpg"
  },
  {
   "id": "a8c6395b-aa04-426f-aa09-284ae1c3a1e5",
   "title": {
    "en": "Tsui no Taimashi \u2015Ender Geister\u30fc"
   },
   "contentRating": "suggestive",
   "score": 0.20977136,
   "languages": [
    "fr",
    "en",
    "it",
    "es",
    "pt-br",
    "id",
    "zh-hk"
   ],
   "coverFileName": "236fc2ac-0b6a-42db-9634-7329174ad1fa.jpg"
  },
  {
   "id": "cf14141c-5051-42a1-a2ec-041a12b8b61a",
   "title": {
    "en": "Final Girl"
   },
   "contentRating": "suggestive",
   "score": 0.20977136,
   "languages": [
    "tr",
    "fr",
    "pt-br",
    "es-la",
    "en"
   ],
   "coverFileName": "5fd15bac-374e-4bf3-85df-e144e6d06e4b.jpg"
  },
  {
   "id": "d590e65a-c3c8-4fd2-a754-1d0c34cf0e91",
   "title": {
    "en": "Biohazard: Heavenly Island"
   },
   "contentRating": "suggestive",
   "score": 0.2049447,
   "languages": [
    "en",
    "hu"
   ],
   "coverFileName": "8fcb4684-5da8-4d67-905e-243a66068445.jpg"
  },
  {
   "id": "e047a92b-1ec7-46c6-a3b2-5f678818df91",
   "title": {
    "en": "Ren'ai Harem Game Shuuryou no Oshirase ga Kuru Koro ni"
   },
   "contentRating": "suggestive",
   "score": 0.20131753,
   "languages": [
    "es-la",
    "ru",
    "en"
   ],
   "coverFileName": "03ec5928-3b13-4f96-8764-5d90fc31d1f0.jpg"
  },
  {
   "id": "9fd3284e-2b60-4e39-adff-31763d2892f1",
   "title": {
    "en": "Highschool of the Dead"
   },
   "contentRating": "suggestive",
   "score": 0.19622314,
   "languages": [
    "en"
   ],
   "coverFileName": "8c0dd009-2461-49c9-a939-675194b213ef.jpg"
  },
  {
   "id": "eb17e1e9-7a26-4173-88fa-6878a7081a59",
   "title": {
    "en": "Infection"
   },
   "contentRating": "suggestive",
   "score": 0.19622314,
   "languages": [
    "pt-br",
    "ru",
    "en",
    "es-la",
    "id",
    "it"
   ],
   "coverFileName": "f559c2dc-8f98-4ab6-9fa1-0db364716d2d.jpg"
  }
 ],
 "updatedAt": "2021-07-18T06:59:22+00:00",
 "coverFileName": "578c165a-3a50-41b3-8838-bdbc8a5f74bb.jpg"
}